LICENSE
MANIFEST.in
README.md
setup.cfg
setup.py
pyasn/__init__.py
pyasn/_version.py
pyasn/mrtx.py
pyasn/pyasn_radix.c
pyasn-utils/pyasn_util_asnames.py
pyasn-utils/pyasn_util_convert.py
pyasn-utils/pyasn_util_download.py
pyasn.egg-info/PKG-INFO
pyasn.egg-info/SOURCES.txt
pyasn.egg-info/dependency_links.txt
pyasn.egg-info/not-zip-safe
pyasn.egg-info/requires.txt
pyasn.egg-info/top_level.txt
pyasn/_radix/radix.c
pyasn/_radix/radix.h
tests/test_PyASN_1_2_aggressive.py
tests/test_comparative.py
tests/test_mrtx.py
tests/test_simple.py