Metadata-Version: 2.1
Name: pyasn
Version: 1.6.2
Summary: Offline IP address to Autonomous System Number lookup module.
Home-page: https://github.com/hadiasghari/pyasn
Maintainer: Hadi Asghari
Maintainer-email: hd.asghari@gmail.com
License: MIT
Keywords: ip asn autonomous system bgp whois prefix radix python routing networking
Classifier: Intended Audience :: Developers
Classifier: Topic :: Software Development :: Libraries :: Python Modules
Classifier: Topic :: System :: Networking
Classifier: License :: OSI Approved :: MIT License
Classifier: Operating System :: OS Independent
Classifier: Programming Language :: Python
Classifier: Programming Language :: Python :: 2
Classifier: Programming Language :: Python :: 3
Provides-Extra: test
License-File: LICENSE
